<annotation>
	<folder>Images</folder>
	<filename>1091715_DF_251_251BDF0490_00782_RAW.jpg</filename>
	<path>C:\Users\admin\OneDrive\Desktop\Images\1091715_DF_251_251BDF0490_00782_RAW.jpg</path>
	<source>
		<database>Unknown</database>
	</source>
	<size>
		<width>1024</width>
		<height>630</height>
		<depth>3</depth>
	</size>
	<segmented>0</segmented>
	<object>
		<name>crack</name>
		<pose>Unspecified</pose>
		<truncated>0</truncated>
		<difficult>0</difficult>
		<bndbox>
			<xmin>699</xmin>
			<ymin>162</ymin>
			<xmax>843</xmax>
			<ymax>311</ymax>
		</bndbox>
	</object>
	<object>
		<name>crack</name>
		<pose>Unspecified</pose>
		<truncated>0</truncated>
		<difficult>0</difficult>
		<bndbox>
			<xmin>839</xmin>
			<ymin>425</ymin>
			<xmax>1014</xmax>
			<ymax>576</ymax>
		</bndbox>
	</object>
</annotation>
