<annotation>
	<folder>Images</folder>
	<filename>917673_RS_290_290RS294095_21815_RAW.jpg</filename>
	<path>C:\Users\admin\OneDrive\Desktop\Images\917673_RS_290_290RS294095_21815_RAW.jpg</path>
	<source>
		<database>Unknown</database>
	</source>
	<size>
		<width>1024</width>
		<height>640</height>
		<depth>3</depth>
	</size>
	<segmented>0</segmented>
	<object>
		<name>hole</name>
		<pose>Unspecified</pose>
		<truncated>1</truncated>
		<difficult>0</difficult>
		<bndbox>
			<xmin>1</xmin>
			<ymin>528</ymin>
			<xmax>241</xmax>
			<ymax>640</ymax>
		</bndbox>
	</object>
	<object>
		<name>crack</name>
		<pose>Unspecified</pose>
		<truncated>0</truncated>
		<difficult>0</difficult>
		<bndbox>
			<xmin>718</xmin>
			<ymin>421</ymin>
			<xmax>819</xmax>
			<ymax>636</ymax>
		</bndbox>
	</object>
</annotation>
