<annotation>
	<folder>Images</folder>
	<filename>994595_RS_386_386RS191729_09740_RAW.jpg</filename>
	<path>C:\Users\admin\OneDrive\Desktop\Images\994595_RS_386_386RS191729_09740_RAW.jpg</path>
	<source>
		<database>Unknown</database>
	</source>
	<size>
		<width>1024</width>
		<height>640</height>
		<depth>3</depth>
	</size>
	<segmented>0</segmented>
	<object>
		<name>crack</name>
		<pose>Unspecified</pose>
		<truncated>0</truncated>
		<difficult>0</difficult>
		<bndbox>
			<xmin>691</xmin>
			<ymin>331</ymin>
			<xmax>951</xmax>
			<ymax>636</ymax>
		</bndbox>
	</object>
	<object>
		<name>crack</name>
		<pose>Unspecified</pose>
		<truncated>1</truncated>
		<difficult>0</difficult>
		<bndbox>
			<xmin>30</xmin>
			<ymin>439</ymin>
			<xmax>353</xmax>
			<ymax>640</ymax>
		</bndbox>
	</object>
	<object>
		<name>crack</name>
		<pose>Unspecified</pose>
		<truncated>0</truncated>
		<difficult>0</difficult>
		<bndbox>
			<xmin>286</xmin>
			<ymin>263</ymin>
			<xmax>425</xmax>
			<ymax>395</ymax>
		</bndbox>
	</object>
</annotation>
